{
    "run": 60,
    "seed": 271,
    "Model": "XGBoost",
    "R2": 0.7590499759732992,
    "RMSE": 0.8984334034804403,
    "MAPE": 0.22549874688637286,
    "Best Config": {
        "n_estimators": 10000,
        "learning_rate": 0.1,
        "n_jobs": -1,
        "proc.max_category_levels": 100,
        "objective": "reg:squarederror",
        "booster": "gbtree"
    },
    "Feature importance": {
        "EC": {
            "importance": 0.848414451389073,
            "stddev": 0.06334450137730982,
            "p_value": 3.7013797668692438e-06,
            "n": 5,
            "p99_high": 0.9788416552390046,
            "p99_low": 0.7179872475391414,
            "normalized_importance": 0.533979749859334
        },
        "SS": {
            "importance": 0.39038605626652745,
            "stddev": 0.011939021536058577,
            "p_value": 1.0484255642360528e-07,
            "n": 5,
            "p99_high": 0.41496866662408594,
            "p99_low": 0.36580344590896896,
            "normalized_importance": 0.24570332145152923
        },
        "pH": {
            "importance": 0.2313791769323819,
            "stddev": 0.013866553902361533,
            "p_value": 1.54057001676023e-06,
            "n": 5,
            "p99_high": 0.2599306030734867,
            "p99_low": 0.20282775079127713,
            "normalized_importance": 0.1456266979171863
        },
        "WT": {
            "importance": 0.11867167468654134,
            "stddev": 0.013968987600855956,
            "p_value": 2.2618905820319627e-05,
            "n": 5,
            "p99_high": 0.1474340132286303,
            "p99_low": 0.08990933614445236,
            "normalized_importance": 0.07469023077195046
        }
    },
    "X_test": [
        [
            210.0,
            5.1,
            25.7,
            7.74
        ],
        [
            155.0,
            4.0,
            18.4,
            7.51
        ],
        [
            115.0,
            3.2,
            21.0,
            7.8
        ],
        [
            571.0,
            25.6,
            18.7,
            7.16
        ],
        [
            16500.0,
            21.3,
            30.5,
            7.25
        ],
        [
            234.0,
            103.0,
            24.9,
            7.2
        ],
        [
            404.0,
            13.3,
            28.2,
            7.67
        ],
        [
            190.0,
            8.8,
            28.0,
            7.55
        ],
        [
            222.0,
            21.0,
            19.9,
            7.19
        ],
        [
            122.0,
            29.5,
            20.0,
            7.29
        ],
        [
            256.0,
            7.0,
            30.6,
            7.64
        ],
        [
            35600.0,
            27.8,
            17.7,
            7.74
        ],
        [
            181.0,
            3.0,
            20.4,
            7.92
        ],
        [
            1850.0,
            15.1,
            18.6,
            7.47
        ],
        [
            194.0,
            10.7,
            27.0,
            7.13
        ],
        [
            1050.0,
            20.8,
            24.0,
            7.23
        ],
        [
            180.0,
            3.8,
            22.0,
            7.62
        ],
        [
            315.0,
            5.6,
            27.5,
            7.56
        ],
        [
            129.0,
            6.6,
            17.2,
            7.64
        ],
        [
            196.0,
            2.6,
            23.1,
            7.56
        ],
        [
            12900.0,
            9.6,
            30.5,
            7.05
        ],
        [
            156.0,
            4.0,
            17.6,
            7.61
        ],
        [
            409.0,
            37.0,
            22.6,
            7.14
        ],
        [
            243.0,
            6.0,
            31.7,
            7.46
        ],
        [
            166.0,
            8.4,
            26.7,
            7.58
        ],
        [
            118.0,
            2.3,
            23.8,
            8.2
        ],
        [
            1670.0,
            34.4,
            18.5,
            7.35
        ],
        [
            17200.0,
            15.5,
            19.9,
            7.4
        ],
        [
            2850.0,
            19.0,
            27.4,
            7.24
        ],
        [
            1130.0,
            32.8,
            20.8,
            7.17
        ],
        [
            322.0,
            11.2,
            32.4,
            8.48
        ],
        [
            186.0,
            11.2,
            18.8,
            7.44
        ],
        [
            326.0,
            8.4,
            30.9,
            8.24
        ],
        [
            113.0,
            6.4,
            25.2,
            7.88
        ],
        [
            177.0,
            7.5,
            17.4,
            7.24
        ],
        [
            37800.0,
            21.4,
            26.1,
            7.69
        ],
        [
            148.0,
            6.0,
            24.1,
            7.73
        ],
        [
            208.0,
            3.6,
            23.9,
            7.59
        ],
        [
            111.0,
            20.0,
            17.5,
            7.5
        ],
        [
            176.0,
            1.9,
            17.8,
            8.15
        ],
        [
            318.0,
            9.9,
            25.9,
            7.13
        ],
        [
            243.0,
            17.1,
            17.2,
            7.44
        ],
        [
            32800.0,
            32.8,
            20.0,
            7.66
        ],
        [
            410.0,
            21.7,
            29.1,
            7.24
        ],
        [
            216.0,
            13.5,
            24.2,
            7.38
        ],
        [
            149.0,
            5.7,
            14.3,
            7.52
        ],
        [
            168.0,
            81.5,
            23.2,
            7.22
        ],
        [
            109.0,
            12.8,
            25.4,
            7.68
        ],
        [
            560.0,
            24.6,
            19.5,
            7.36
        ],
        [
            31300.0,
            11.9,
            31.1,
            7.77
        ],
        [
            31800.0,
            16.9,
            21.2,
            7.84
        ],
        [
            184.0,
            3.4,
            19.7,
            7.3
        ],
        [
            165.0,
            272.0,
            26.4,
            7.59
        ],
        [
            16100.0,
            17.2,
            17.1,
            7.11
        ],
        [
            37200.0,
            14.8,
            30.9,
            7.77
        ],
        [
            35600.0,
            27.8,
            17.7,
            7.74
        ],
        [
            891.0,
            13.0,
            17.8,
            7.37
        ],
        [
            28100.0,
            21.2,
            25.7,
            7.68
        ],
        [
            2060.0,
            17.5,
            18.5,
            7.3
        ],
        [
            14000.0,
            29.2,
            24.2,
            7.21
        ],
        [
            157.0,
            3.6,
            29.4,
            8.69
        ],
        [
            166.0,
            6.6,
            27.7,
            7.71
        ],
        [
            7900.0,
            14.6,
            19.8,
            7.28
        ],
        [
            668.0,
            60.2,
            23.4,
            7.22
        ],
        [
            33300.0,
            6.3,
            19.8,
            7.89
        ],
        [
            219.0,
            3.9,
            26.6,
            8.04
        ],
        [
            164.0,
            14.9,
            17.8,
            7.17
        ],
        [
            32400.0,
            32.8,
            19.1,
            7.51
        ],
        [
            205.0,
            1.8,
            22.6,
            8.49
        ],
        [
            33100.0,
            20.5,
            20.0,
            7.7
        ],
        [
            213.0,
            7.4,
            24.3,
            7.2
        ],
        [
            166.0,
            3.4,
            25.6,
            7.81
        ],
        [
            394.0,
            23.8,
            19.0,
            7.44
        ],
        [
            16100.0,
            16.0,
            19.4,
            7.3
        ],
        [
            227.0,
            3.6,
            31.2,
            8.4
        ],
        [
            4370.0,
            15.0,
            22.0,
            7.03
        ],
        [
            1000.0,
            23.7,
            25.5,
            7.31
        ],
        [
            736.0,
            22.3,
            26.9,
            7.27
        ],
        [
            653.0,
            11.6,
            17.2,
            7.64
        ],
        [
            192.0,
            9.6,
            15.3,
            7.4
        ],
        [
            35600.0,
            15.2,
            23.5,
            8.0
        ],
        [
            2850.0,
            19.0,
            27.4,
            7.24
        ],
        [
            414.0,
            12.4,
            31.1,
            7.77
        ],
        [
            16800.0,
            14.2,
            17.1,
            7.52
        ],
        [
            198.0,
            5.5,
            21.5,
            7.68
        ],
        [
            134.0,
            5.3,
            26.7,
            8.02
        ],
        [
            454.0,
            38.6,
            19.4,
            7.22
        ],
        [
            173.0,
            12.2,
            28.8,
            7.42
        ],
        [
            5050.0,
            12.9,
            29.8,
            7.21
        ],
        [
            12800.0,
            13.8,
            18.9,
            7.45
        ],
        [
            1520.0,
            31.2,
            25.3,
            7.4
        ],
        [
            25800.0,
            15.9,
            20.0,
            7.64
        ],
        [
            254.0,
            4.8,
            28.7,
            7.53
        ],
        [
            212.0,
            4.0,
            19.2,
            7.32
        ],
        [
            150.0,
            38.2,
            16.7,
            7.14
        ],
        [
            250.0,
            6.4,
            23.2,
            7.54
        ],
        [
            32000.0,
            21.9,
            20.4,
            7.58
        ],
        [
            202.0,
            19.3,
            19.7,
            7.04
        ],
        [
            15000.0,
            33.2,
            29.8,
            7.33
        ],
        [
            200.0,
            2.8,
            16.6,
            7.5
        ],
        [
            103.0,
            32.6,
            25.2,
            7.03
        ],
        [
            36400.0,
            31.3,
            28.2,
            7.91
        ],
        [
            416.0,
            46.8,
            28.9,
            7.3
        ],
        [
            224.0,
            92.0,
            26.9,
            7.38
        ],
        [
            402.0,
            30.2,
            20.4,
            7.36
        ],
        [
            90.0,
            13.4,
            25.2,
            7.38
        ],
        [
            22400.0,
            15.7,
            26.4,
            7.34
        ],
        [
            32700.0,
            11.3,
            30.9,
            7.59
        ],
        [
            172.0,
            50.1,
            23.8,
            7.56
        ],
        [
            916.0,
            11.8,
            22.6,
            7.3
        ],
        [
            17300.0,
            16.3,
            29.7,
            7.2
        ],
        [
            972.0,
            22.2,
            21.2,
            7.53
        ],
        [
            31600.0,
            51.4,
            26.8,
            7.56
        ],
        [
            1030.0,
            15.6,
            24.0,
            7.26
        ],
        [
            6940.0,
            17.2,
            21.1,
            7.42
        ],
        [
            7260.0,
            20.0,
            19.8,
            7.33
        ],
        [
            32000.0,
            17.8,
            26.4,
            7.56
        ],
        [
            2430.0,
            15.8,
            23.0,
            7.2
        ],
        [
            32400.0,
            24.1,
            16.4,
            7.8
        ],
        [
            15100.0,
            28.0,
            25.7,
            7.47
        ],
        [
            288.0,
            7.2,
            32.0,
            7.8
        ],
        [
            171.0,
            4.6,
            23.5,
            7.98
        ],
        [
            216.0,
            2.2,
            19.4,
            7.56
        ],
        [
            736.0,
            22.3,
            26.9,
            7.27
        ],
        [
            242.0,
            45.2,
            19.9,
            7.51
        ],
        [
            42100.0,
            27.9,
            29.9,
            7.92
        ],
        [
            4870.0,
            47.0,
            27.6,
            7.52
        ],
        [
            113.0,
            12.7,
            23.1,
            7.31
        ],
        [
            11200.0,
            32.0,
            22.1,
            7.32
        ],
        [
            7740.0,
            24.8,
            20.1,
            7.47
        ],
        [
            494.0,
            17.2,
            19.3,
            7.36
        ],
        [
            239.0,
            15.4,
            25.5,
            7.21
        ],
        [
            36600.0,
            10.2,
            26.4,
            7.88
        ],
        [
            170.0,
            3.2,
            19.7,
            7.57
        ],
        [
            470.0,
            24.6,
            29.7,
            7.2
        ]
    ],
    "y_test": [
        1.0,
        1.0,
        1.0,
        7.25,
        4.0,
        5.0,
        4.25,
        1.5,
        2.5,
        1.5,
        1.0,
        3.0,
        1.0,
        2.75,
        1.0,
        4.0,
        2.0,
        1.5,
        1.0,
        1.0,
        4.5,
        1.0,
        6.5,
        3.25,
        1.0,
        1.0,
        4.0,
        4.5,
        6.0,
        5.5,
        2.25,
        3.25,
        1.5,
        1.0,
        1.0,
        4.0,
        1.0,
        1.0,
        1.0,
        1.0,
        4.5,
        3.0,
        2.5,
        6.25,
        1.5,
        1.0,
        3.25,
        1.0,
        6.3,
        3.5,
        2.75,
        1.0,
        3.75,
        2.75,
        3.5,
        3.25,
        6.8,
        2.75,
        3.0,
        4.0,
        1.0,
        2.0,
        3.5,
        3.25,
        2.25,
        1.0,
        1.0,
        3.25,
        1.0,
        3.3,
        1.5,
        1.0,
        7.3,
        2.75,
        1.0,
        3.5,
        7.25,
        7.25,
        3.5,
        1.5,
        2.25,
        6.0,
        3.5,
        2.75,
        1.0,
        1.0,
        5.5,
        1.0,
        5.5,
        2.75,
        4.0,
        2.75,
        1.5,
        1.0,
        1.5,
        2.75,
        4.0,
        4.5,
        4.0,
        1.0,
        1.5,
        2.0,
        6.5,
        5.25,
        4.0,
        1.0,
        3.5,
        3.5,
        2.75,
        6.0,
        4.0,
        6.25,
        4.0,
        5.0,
        4.25,
        4.5,
        3.5,
        3.5,
        3.25,
        3.25,
        1.0,
        1.0,
        1.0,
        7.3,
        3.75,
        2.5,
        5.0,
        1.0,
        4.0,
        2.5,
        6.75,
        4.0,
        2.0,
        1.0,
        5.0
    ],
    "y_pred": [
        0.927034318447113,
        1.1689215898513794,
        1.12001371383667,
        5.599220275878906,
        4.826913356781006,
        3.8838465213775635,
        4.066357135772705,
        1.2670207023620605,
        3.8580729961395264,
        1.5423945188522339,
        1.4760576486587524,
        3.0055713653564453,
        1.1135073900222778,
        4.286369800567627,
        2.189639091491699,
        6.248242378234863,
        1.207085132598877,
        1.5990713834762573,
        1.0574501752853394,
        1.1140280961990356,
        4.318229675292969,
        1.0208439826965332,
        4.052814483642578,
        2.7249786853790283,
        0.9893670082092285,
        1.0287973880767822,
        4.259406089782715,
        4.0262451171875,
        5.163641452789307,
        5.879148006439209,
        3.649355173110962,
        1.4843850135803223,
        2.6484599113464355,
        1.0223912000656128,
        1.8300269842147827,
        3.761431932449341,
        1.0335919857025146,
        1.2295973300933838,
        1.062878966331482,
        1.0936415195465088,
        3.5039114952087402,
        3.054611921310425,
        3.1947715282440186,
        6.078465461730957,
        2.339360475540161,
        1.0499720573425293,
        2.496720552444458,
        1.2998356819152832,
        6.25979471206665,
        2.4887218475341797,
        2.3227763175964355,
        1.1012029647827148,
        3.8227591514587402,
        3.279623031616211,
        2.4515936374664307,
        3.0055713653564453,
        6.645632266998291,
        3.6798017024993896,
        5.844746112823486,
        4.6521124839782715,
        1.0387927293777466,
        0.9676114916801453,
        3.351224184036255,
        4.106443405151367,
        1.5892932415008545,
        0.976866602897644,
        2.525942087173462,
        2.9424686431884766,
        1.067011833190918,
        3.103498935699463,
        1.8082865476608276,
        0.9784384965896606,
        5.276633262634277,
        3.605228900909424,
        1.0590509176254272,
        3.881870746612549,
        5.613539695739746,
        5.762221813201904,
        3.1807215213775635,
        1.485252857208252,
        2.2209391593933105,
        5.163641452789307,
        3.628603935241699,
        2.111295461654663,
        1.173282504081726,
        0.9843063354492188,
        1.8600890636444092,
        1.8213750123977661,
        5.521795749664307,
        2.6629254817962646,
        5.523876190185547,
        2.744426727294922,
        1.1883200407028198,
        1.2878999710083008,
        2.18186354637146,
        1.1646302938461304,
        3.8733482360839844,
        2.6919167041778564,
        4.528375148773193,
        1.1259937286376953,
        2.3467884063720703,
        2.6980037689208984,
        5.208446502685547,
        3.8620495796203613,
        6.038649082183838,
        1.2514725923538208,
        4.0136332511901855,
        2.6751067638397217,
        3.2533087730407715,
        6.379568576812744,
        4.373157501220703,
        5.992289066314697,
        3.306786298751831,
        6.154802322387695,
        4.4413957595825195,
        4.1853718757629395,
        3.3965446949005127,
        5.378345966339111,
        3.009904623031616,
        4.376014709472656,
        1.586629033088684,
        1.0786652565002441,
        1.1383051872253418,
        5.762221813201904,
        3.896146297454834,
        3.3828141689300537,
        4.752395153045654,
        1.3127185106277466,
        4.093862056732178,
        3.5093162059783936,
        6.406863689422607,
        3.4127273559570312,
        2.250443458557129,
        1.2059276103973389,
        6.1918158531188965
    ]
}