{
    "run": 76,
    "seed": 907,
    "Model": "LightGBM",
    "R2": 0.6945812958655369,
    "RMSE": 0.9979446246742641,
    "MAPE": 0.24244951757930536,
    "Best Config": {
        "learning_rate": 0.05
    },
    "Feature importance": {
        "EC": {
            "importance": 1.0600612470288173,
            "stddev": 0.05575278192294249,
            "p_value": 9.14794470972784e-07,
            "n": 5,
            "p99_high": 1.1748569955934929,
            "p99_low": 0.9452654984641418,
            "normalized_importance": 0.6213073056276259
        },
        "SS": {
            "importance": 0.3341949774360084,
            "stddev": 0.029477191392230345,
            "p_value": 7.1884350126483445e-06,
            "n": 5,
            "p99_high": 0.3948889219306924,
            "p99_low": 0.2735010329413244,
            "normalized_importance": 0.19587338143623986
        },
        "pH": {
            "importance": 0.2093232302545182,
            "stddev": 0.012845541565856971,
            "p_value": 1.6933380414921793e-06,
            "n": 5,
            "p99_high": 0.23577237788286992,
            "p99_low": 0.1828740826261665,
            "normalized_importance": 0.12268541328081432
        },
        "WT": {
            "importance": 0.10259917448247322,
            "stddev": 0.009342547831675036,
            "p_value": 8.159826352055794e-06,
            "n": 5,
            "p99_high": 0.12183560959562567,
            "p99_low": 0.08336273936932076,
            "normalized_importance": 0.060133899655319824
        }
    },
    "X_test": [
        [
            34600.0,
            38.3,
            23.4,
            7.83
        ],
        [
            242.0,
            17.8,
            21.2,
            7.06
        ],
        [
            1670.0,
            34.4,
            18.5,
            7.35
        ],
        [
            219.0,
            3.9,
            26.6,
            8.04
        ],
        [
            140.0,
            2.6,
            27.0,
            8.53
        ],
        [
            3570.0,
            30.0,
            30.2,
            7.18
        ],
        [
            203.0,
            6.0,
            21.2,
            7.64
        ],
        [
            28100.0,
            21.2,
            25.7,
            7.68
        ],
        [
            190.0,
            8.8,
            28.0,
            7.55
        ],
        [
            264.0,
            6.0,
            31.1,
            8.18
        ],
        [
            128.0,
            8.2,
            25.5,
            7.62
        ],
        [
            171.0,
            1.7,
            15.3,
            7.7
        ],
        [
            32800.0,
            32.8,
            20.0,
            7.66
        ],
        [
            103.0,
            28.2,
            25.8,
            7.2
        ],
        [
            250.0,
            6.4,
            23.2,
            7.54
        ],
        [
            7440.0,
            24.1,
            20.0,
            7.31
        ],
        [
            208.0,
            34.6,
            19.6,
            7.28
        ],
        [
            31300.0,
            11.9,
            31.1,
            7.77
        ],
        [
            1310.0,
            22.7,
            30.1,
            7.33
        ],
        [
            6940.0,
            17.2,
            21.1,
            7.42
        ],
        [
            17300.0,
            16.3,
            29.7,
            7.2
        ],
        [
            210.0,
            2.0,
            16.9,
            7.48
        ],
        [
            181.0,
            3.2,
            20.1,
            7.27
        ],
        [
            212.0,
            6.4,
            29.6,
            7.87
        ],
        [
            214.0,
            4.2,
            21.9,
            7.49
        ],
        [
            16100.0,
            17.2,
            17.1,
            7.11
        ],
        [
            411.0,
            17.0,
            30.4,
            7.31
        ],
        [
            185.0,
            9.6,
            22.6,
            7.82
        ],
        [
            182.0,
            41.4,
            19.9,
            7.24
        ],
        [
            93.0,
            17.2,
            25.8,
            7.55
        ],
        [
            35600.0,
            24.8,
            30.4,
            7.76
        ],
        [
            250.0,
            183.0,
            24.0,
            7.3
        ],
        [
            233.0,
            15.0,
            17.1,
            7.32
        ],
        [
            626.0,
            24.0,
            29.8,
            7.25
        ],
        [
            1010.0,
            25.5,
            19.5,
            7.34
        ],
        [
            2680.0,
            41.8,
            25.5,
            7.28
        ],
        [
            172.0,
            50.1,
            23.8,
            7.56
        ],
        [
            120.0,
            62.7,
            18.0,
            7.14
        ],
        [
            169.0,
            19.4,
            19.5,
            7.34
        ],
        [
            184.0,
            29.5,
            23.3,
            7.62
        ],
        [
            38400.0,
            21.5,
            23.5,
            7.7
        ],
        [
            420.0,
            22.5,
            25.6,
            7.32
        ],
        [
            30500.0,
            26.1,
            19.7,
            7.6
        ],
        [
            176.0,
            1.9,
            17.8,
            8.15
        ],
        [
            1070.0,
            44.5,
            26.5,
            7.39
        ],
        [
            122.0,
            29.5,
            20.0,
            7.29
        ],
        [
            244.0,
            7.7,
            29.3,
            7.47
        ],
        [
            192.0,
            2.2,
            23.7,
            8.1
        ],
        [
            313.0,
            7.9,
            32.0,
            8.02
        ],
        [
            115.0,
            3.2,
            21.0,
            7.8
        ],
        [
            124.0,
            4.4,
            25.0,
            8.24
        ],
        [
            740.0,
            45.1,
            22.7,
            7.22
        ],
        [
            222.0,
            21.0,
            19.9,
            7.19
        ],
        [
            189.0,
            2.4,
            17.9,
            7.6
        ],
        [
            3280.0,
            16.1,
            16.5,
            7.4
        ],
        [
            183.0,
            5.2,
            27.9,
            7.73
        ],
        [
            34300.0,
            30.2,
            23.5,
            7.78
        ],
        [
            744.0,
            19.5,
            25.8,
            7.32
        ],
        [
            208.0,
            3.6,
            23.9,
            7.59
        ],
        [
            173.0,
            12.2,
            28.8,
            7.42
        ],
        [
            202.0,
            17.7,
            15.7,
            7.4
        ],
        [
            7880.0,
            15.0,
            27.6,
            7.2
        ],
        [
            34300.0,
            12.8,
            25.0,
            7.78
        ],
        [
            32000.0,
            17.8,
            26.4,
            7.56
        ],
        [
            24300.0,
            22.2,
            29.8,
            7.69
        ],
        [
            233.0,
            6.9,
            19.3,
            7.44
        ],
        [
            891.0,
            13.0,
            17.8,
            7.37
        ],
        [
            351.0,
            12.3,
            28.6,
            7.51
        ],
        [
            327.0,
            13.9,
            23.7,
            7.14
        ],
        [
            184.0,
            4.6,
            30.2,
            7.96
        ],
        [
            228.0,
            2.5,
            21.5,
            7.56
        ],
        [
            224.0,
            40.5,
            28.4,
            7.2
        ],
        [
            286.0,
            22.0,
            25.9,
            7.3
        ],
        [
            4500.0,
            33.5,
            21.3,
            7.3
        ],
        [
            150.0,
            7.9,
            17.6,
            7.24
        ],
        [
            319.0,
            11.3,
            27.4,
            7.32
        ],
        [
            309.0,
            32.5,
            18.8,
            7.24
        ],
        [
            12100.0,
            15.8,
            17.6,
            7.18
        ],
        [
            464.0,
            28.1,
            22.4,
            7.4
        ],
        [
            38700.0,
            12.4,
            28.8,
            7.81
        ],
        [
            164.0,
            14.9,
            17.8,
            7.17
        ],
        [
            230.0,
            6.8,
            31.7,
            7.72
        ],
        [
            191.0,
            11.6,
            24.4,
            7.25
        ],
        [
            13100.0,
            24.8,
            23.1,
            7.26
        ],
        [
            131.0,
            1.8,
            18.6,
            7.7
        ],
        [
            90.0,
            13.4,
            25.2,
            7.38
        ],
        [
            409.0,
            37.0,
            22.6,
            7.14
        ],
        [
            201.0,
            11.2,
            28.2,
            7.62
        ],
        [
            205.0,
            9.7,
            28.5,
            7.75
        ],
        [
            16800.0,
            14.2,
            17.1,
            7.52
        ],
        [
            37200.0,
            14.8,
            30.9,
            7.77
        ],
        [
            14700.0,
            23.7,
            24.9,
            7.27
        ],
        [
            264.0,
            19.5,
            32.0,
            9.16
        ],
        [
            171.0,
            4.6,
            23.5,
            7.98
        ],
        [
            676.0,
            25.9,
            19.1,
            7.46
        ],
        [
            763.0,
            29.0,
            18.8,
            7.34
        ],
        [
            225.0,
            5.4,
            20.5,
            7.82
        ],
        [
            220.0,
            3.3,
            25.0,
            7.5
        ],
        [
            216.0,
            7.3,
            27.3,
            7.37
        ],
        [
            542.0,
            17.3,
            22.4,
            7.28
        ],
        [
            19100.0,
            15.6,
            19.6,
            7.54
        ],
        [
            3840.0,
            23.8,
            27.1,
            7.1
        ],
        [
            5650.0,
            17.3,
            24.2,
            7.07
        ],
        [
            1520.0,
            31.2,
            25.3,
            7.4
        ],
        [
            331.0,
            11.0,
            32.2,
            8.18
        ],
        [
            250.0,
            7.9,
            20.8,
            7.71
        ],
        [
            470.0,
            24.6,
            29.7,
            7.2
        ],
        [
            2440.0,
            22.1,
            19.8,
            7.3
        ],
        [
            9030.0,
            23.3,
            20.3,
            7.32
        ],
        [
            30000.0,
            14.8,
            30.0,
            7.56
        ],
        [
            152.0,
            9.6,
            28.2,
            7.62
        ],
        [
            1850.0,
            15.1,
            18.6,
            7.47
        ],
        [
            12200.0,
            29.2,
            28.6,
            7.28
        ],
        [
            347.0,
            32.5,
            29.7,
            7.38
        ],
        [
            100.0,
            15.8,
            27.0,
            7.55
        ],
        [
            202.0,
            7.2,
            19.6,
            7.3
        ],
        [
            26000.0,
            28.9,
            23.2,
            7.44
        ],
        [
            1840.0,
            41.8,
            29.3,
            7.29
        ],
        [
            42100.0,
            25.5,
            30.2,
            7.91
        ],
        [
            1130.0,
            32.8,
            20.8,
            7.17
        ],
        [
            560.0,
            24.6,
            19.5,
            7.36
        ],
        [
            972.0,
            22.2,
            21.2,
            7.53
        ],
        [
            9420.0,
            20.4,
            20.1,
            7.14
        ],
        [
            33100.0,
            20.5,
            20.0,
            7.7
        ],
        [
            165.0,
            272.0,
            26.4,
            7.59
        ],
        [
            175.0,
            3.5,
            18.7,
            7.4
        ],
        [
            32700.0,
            11.3,
            30.9,
            7.59
        ],
        [
            9340.0,
            10.6,
            19.2,
            7.24
        ],
        [
            21300.0,
            28.0,
            23.7,
            7.49
        ],
        [
            203.0,
            23.2,
            27.2,
            7.29
        ],
        [
            158.0,
            1.6,
            17.1,
            7.59
        ],
        [
            430.0,
            14.7,
            28.9,
            7.28
        ],
        [
            30100.0,
            40.5,
            28.8,
            7.76
        ],
        [
            164.0,
            40.0,
            23.2,
            7.5
        ],
        [
            212.0,
            7.6,
            18.2,
            7.52
        ]
    ],
    "y_test": [
        3.0,
        4.0,
        4.0,
        1.0,
        1.0,
        6.0,
        2.75,
        2.75,
        1.5,
        1.0,
        1.0,
        1.0,
        2.5,
        2.0,
        2.75,
        2.5,
        2.0,
        3.5,
        6.5,
        4.3,
        4.0,
        1.5,
        1.0,
        1.0,
        1.0,
        2.75,
        6.0,
        1.5,
        2.75,
        1.0,
        2.5,
        4.5,
        3.5,
        6.5,
        7.25,
        4.5,
        2.75,
        2.25,
        1.5,
        2.0,
        3.25,
        4.0,
        3.3,
        1.0,
        6.5,
        1.5,
        4.0,
        1.0,
        2.0,
        1.0,
        1.0,
        3.0,
        2.5,
        1.0,
        5.5,
        1.0,
        3.25,
        3.0,
        1.0,
        1.0,
        1.5,
        3.5,
        2.0,
        3.5,
        4.0,
        2.0,
        6.75,
        4.25,
        3.75,
        1.0,
        1.0,
        4.0,
        3.25,
        5.0,
        1.0,
        2.75,
        6.5,
        3.5,
        6.5,
        2.75,
        1.0,
        1.0,
        2.8,
        5.0,
        1.5,
        1.0,
        4.0,
        1.0,
        1.0,
        2.75,
        3.5,
        4.0,
        1.5,
        1.0,
        4.0,
        7.25,
        1.5,
        1.0,
        1.0,
        6.75,
        2.0,
        4.0,
        2.75,
        4.0,
        3.5,
        1.0,
        5.0,
        6.5,
        5.0,
        3.5,
        1.0,
        2.75,
        6.5,
        6.25,
        1.0,
        1.5,
        4.25,
        4.0,
        4.0,
        5.5,
        6.3,
        6.25,
        4.0,
        3.25,
        3.75,
        1.0,
        3.5,
        2.75,
        4.0,
        3.75,
        1.0,
        6.75,
        3.25,
        1.5,
        1.5
    ],
    "y_pred": [
        3.213587999343872,
        3.815793991088867,
        3.8072595596313477,
        0.8025292158126831,
        0.9404751062393188,
        5.737203121185303,
        1.2950795888900757,
        3.468594789505005,
        1.2602849006652832,
        1.137344479560852,
        1.0467066764831543,
        0.953209638595581,
        2.792782783508301,
        2.4983038902282715,
        1.5375453233718872,
        4.032790660858154,
        3.117596387863159,
        2.8041787147521973,
        6.138948917388916,
        4.34662389755249,
        4.159972190856934,
        1.0645568370819092,
        1.090530276298523,
        1.0855610370635986,
        1.1142569780349731,
        3.8673250675201416,
        5.8971099853515625,
        1.8581597805023193,
        2.039114475250244,
        0.9640308022499084,
        3.3127174377441406,
        4.258922576904297,
        2.764497995376587,
        6.503597736358643,
        5.527776718139648,
        4.950590133666992,
        3.163249969482422,
        2.0256760120391846,
        2.027806282043457,
        2.455233573913574,
        3.6031556129455566,
        6.896487712860107,
        3.357429265975952,
        0.7575383186340332,
        4.932953834533691,
        1.610506534576416,
        1.1414358615875244,
        1.048483967781067,
        2.399726390838623,
        0.9556519389152527,
        0.9949793219566345,
        4.512216091156006,
        4.6065897941589355,
        1.5180915594100952,
        5.380901336669922,
        1.2658116817474365,
        3.2144665718078613,
        6.853621006011963,
        1.0975887775421143,
        1.7789002656936646,
        2.993419647216797,
        3.8866801261901855,
        2.5703625679016113,
        3.0672342777252197,
        3.1215322017669678,
        1.698625087738037,
        6.711447715759277,
        4.10054874420166,
        4.2302775382995605,
        1.2095823287963867,
        0.9901947379112244,
        3.927755117416382,
        5.359809398651123,
        4.946942329406738,
        1.0860214233398438,
        3.6170287132263184,
        4.299044132232666,
        3.8709118366241455,
        6.177615165710449,
        2.5445902347564697,
        2.457674264907837,
        1.1386278867721558,
        2.5811080932617188,
        3.3018057346343994,
        1.1821961402893066,
        0.9325260519981384,
        6.396890163421631,
        0.9315358400344849,
        0.6893228888511658,
        2.1588902473449707,
        2.679687261581421,
        4.3782525062561035,
        3.8670411109924316,
        1.2886512279510498,
        4.841067314147949,
        3.9224884510040283,
        1.7412906885147095,
        1.0628612041473389,
        0.7769542932510376,
        6.609133243560791,
        2.3800880908966064,
        5.711880207061768,
        4.340651035308838,
        4.883707523345947,
        2.1641504764556885,
        1.5950263738632202,
        6.460440158843994,
        5.247532367706299,
        4.035898208618164,
        2.719418525695801,
        1.0022141933441162,
        4.490100383758545,
        4.692924976348877,
        4.056273460388184,
        1.0191017389297485,
        1.3630218505859375,
        4.12591028213501,
        4.608148574829102,
        2.6456992626190186,
        4.510152816772461,
        6.7033538818359375,
        6.208940505981445,
        3.6656460762023926,
        3.2995855808258057,
        4.052044868469238,
        1.8184393644332886,
        3.164482355117798,
        3.5929300785064697,
        3.7333028316497803,
        2.927035331726074,
        0.9649651050567627,
        5.902950286865234,
        3.2245795726776123,
        2.246655225753784,
        1.1571228504180908
    ]
}